terraflex/__init__.py
terraflex/__main__.py
terraflex/cli/__init__.py
terraflex/cli/builders/__init__.py
terraflex/cli/builders/encryption_transformer.py
terraflex/cli/builders/git_storage.py
terraflex/cli/builders/local_storage.py
terraflex/cli/builders/storage_provider.py
terraflex/cli/builders/wizard.py
terraflex/cli/cli.py
terraflex/plugins/__init__.py
terraflex/plugins/encryption_transformation/__init__.py
terraflex/plugins/encryption_transformation/age/__init__.py
terraflex/plugins/encryption_transformation/age/controller.py
terraflex/plugins/encryption_transformation/age/downloader.py
terraflex/plugins/encryption_transformation/age/provider.py
terraflex/plugins/encryption_transformation/encryption_base.py
terraflex/plugins/encryption_transformation/encryption_transformation_provider.py
terraflex/plugins/envvar_storage_provider/__init__.py
terraflex/plugins/envvar_storage_provider/envvar_storage_provider.py
terraflex/plugins/git_storage_provider/__init__.py
terraflex/plugins/git_storage_provider/git_storage_provider.py
terraflex/plugins/local_storage_provider/__init__.py
terraflex/plugins/local_storage_provider/local_storage_provider.py
terraflex/plugins/onepassword_storage_provider/__init__.py
terraflex/plugins/onepassword_storage_provider/onepassword_storage_provider.py
terraflex/server/__init__.py
terraflex/server/app.py
terraflex/server/base_state_lock_provider.py
terraflex/server/config.py
terraflex/server/storage_provider_base.py
terraflex/server/tf_state_lock_controller.py
terraflex/server/transformation_base.py
terraflex/utils/__init__.py
terraflex/utils/binary_controller.py
terraflex/utils/dependency_downloader.py
terraflex/utils/dependency_manager.py
terraflex/utils/plugins.py
terraflex-0.4.2.dist-info/LICENSE
terraflex-0.4.2.dist-info/METADATA
terraflex-0.4.2.dist-info/WHEEL
terraflex-0.4.2.dist-info/entry_points.txt
terraflex-0.4.2.dist-info/RECORD
