Metadata-Version: 2.1
Name: terraflex
Version: 0.4.2
Summary: 
Home-page: https://github.com/IamShobe/terraflex
Author: Elran Shefer
Requires-Python: >=3.11,<4.0
Classifier: Programming Language :: Python :: 3
Classifier: Programming Language :: Python :: 3.11
Classifier: Programming Language :: Python :: 3.12
Requires-Dist: fastapi[standard] (>=0.112.2,<0.113.0)
Requires-Dist: httpx (>=0.27.2,<0.28.0)
Requires-Dist: pydantic (>=2.8.2,<3.0.0)
Requires-Dist: pydantic-settings (>=2.4.0,<3.0.0)
Requires-Dist: pyyaml (>=6.0.2,<7.0.0)
Requires-Dist: questionary (>=2.0.1,<3.0.0)
Requires-Dist: requests (>=2.32.3,<3.0.0)
Requires-Dist: rich (>=13.8.1,<14.0.0)
Requires-Dist: semver (>=3.0.2,<4.0.0)
Requires-Dist: typer (>=0.12.5,<0.13.0)
Requires-Dist: xdg-base-dirs (>=6.0.1,<7.0.0)
